Metadata-Version: 2.1
Name: extrac
Version: 0.8.0
Summary: One magic word to unpack archive.
Author-Email: belingud <zyx@lte.ink>
License: MIT
Classifier: Programming Language :: Python :: 3
Classifier: License :: OSI Approved :: MIT License
Classifier: Operating System :: OS Independent
Requires-Python: >=3.8
Requires-Dist: filetype>=1.2.0
Requires-Dist: rarfile>=4.2
Requires-Dist: py7zr>=0.21.1
Requires-Dist: zstandard>=0.22.0
Requires-Dist: arpy>=2.3.0
Requires-Dist: cabarchive>=0.2.4
Requires-Dist: click>=8.1.7
